{
  "api_detail_url": "http://www.giantbomb.com/api/game/3030-45255/",
  "deck": "A randomly generated sandbox action RPG where the player constructs their own airship and sets out on adventure.",
  "id": 45255,
  "image": null,
  "name": "Airship Q",
  "original_release_date": "2015-11-19 00:00:00",
  "platforms": [
    {
      "api_detail_url": "http://www.giantbomb.com/api/platform/3045-94/",
      "id": 94,
      "name": "PC",
      "site_detail_url": "http://www.giantbomb.com/pc/3045-94/",
      "abbreviation": "PC"
    },
    {
      "api_detail_url": "http://www.giantbomb.com/api/platform/3045-143/",
      "id": 143,
      "name": "PlayStation Network (Vita)",
      "site_detail_url": "http://www.giantbomb.com/playstation-network-vita/3045-143/",
      "abbreviation": "PSNV"
    },
    {
      "api_detail_url": "http://www.giantbomb.com/api/platform/3045-146/",
      "id": 146,
      "name": "PlayStation 4",
      "site_detail_url": "http://www.giantbomb.com/playstation-4/3045-146/",
      "abbreviation": "PS4"
    }
  ],
  "site_detail_url": "http://www.giantbomb.com/airship-q/3030-45255/",
  "images": [],
  "videos": [],
  "genres": [
    {
      "api_detail_url": "http://www.giantbomb.com/api/genre/3060-1/",
      "id": 1,
      "name": "Action",
      "site_detail_url": "http://www.giantbomb.com/games/?wikiSlug=action&wikiTypeId=3060&wikiId=1&genre=1"
    },
    {
      "api_detail_url": "http://www.giantbomb.com/api/genre/3060-5/",
      "id": 5,
      "name": "Role-Playing",
      "site_detail_url": "http://www.giantbomb.com/games/?wikiSlug=role-playing&wikiTypeId=3060&wikiId=5&genre=5"
    }
  ],
  "releases": [
    {
      "api_detail_url": "http://www.giantbomb.com/api/release/3050-143183/",
      "id": 143183,
      "name": "Airship Q",
      "site_detail_url": "http://www.giantbomb.com/airship-q/3030-45255/releases/"
    }
  ]
}
